{
  "apiTitle": "1Forge Finance APIs",
  "apiVersion": "0.0.1",
  "apiFileName": "1forge.com-0.0.1-swagger.yaml",
  "apiFormat": "OPENAPI",
  "measurementDate": "2019/12/13",
  "measurement": [
    {
      "metricName": "NumberOfRootPaths",
      "metricValue": 2.0,
      "additionalInformation": "all root paths: /symbols,/quotes"
    },
    {
      "metricName": "WeightedServiceInterfaceCount",
      "metricValue": 2.0,
      "additionalInformation": "Number of different operations: 2"
    },
    {
      "metricName": "ServiceInterfaceDataCohesion",
      "metricValue": 0.0,
      "additionalInformation": "Metric value range: [0-1]; Set of pairwise operations with at least one common parameter: []; Set of pairwise operations with common return type: []; Number of operations: 2.0"
    },
    {
      "metricName": "LongestPath",
      "metricValue": 1.0,
      "additionalInformation": "Longest path: /quotes, Length: 1"
    },
    {
      "metricName": "BiggestRootCoverage",
      "metricValue": 0.5,
      "additionalInformation": "Biggest root coverage: /symbols with 1 operation(s) from overall 2 operation(s)"
    },
    {
      "metricName": "DataWeight",
      "metricValue": 0.0
    },
    {
      "metricName": "LackOfMessageLevelCohesion",
      "metricValue": 1.0
    },
    {
      "metricName": "ArgumentsPerOperation",
      "metricValue": 0.0
    },
    {
      "metricName": "DistinctMessageRatio",
      "metricValue": 0.5
    },
    {
      "metricName": "AveragePathLength",
      "metricValue": 1.0
    }
  ]
}