{
  "apiTitle": "StreamAnalyticsManagementClient",
  "apiVersion": "2016-03-01",
  "apiFileName": "azure.com-streamanalytics-inputs-2016-03-01-swagger.yaml",
  "apiFormat": "OPENAPI",
  "measurementDate": "2019/12/13",
  "measurement": [
    {
      "metricName": "DistinctMessageRatio",
      "metricValue": 0.5333
    },
    {
      "metricName": "BiggestRootCoverage",
      "metricValue": 1.0,
      "additionalInformation": "Biggest root coverage: /subscriptions with 6 operation(s) from overall 6 operation(s)"
    },
    {
      "metricName": "LackOfMessageLevelCohesion",
      "metricValue": 0.5974
    },
    {
      "metricName": "ArgumentsPerOperation",
      "metricValue": 6.0
    },
    {
      "metricName": "LongestPath",
      "metricValue": 11.0,
      "additionalInformation": "Longest path: /subscriptions/{subscriptionId}/resourcegroups/{resourceGroupName}/providers/Microsoft.StreamAnalytics/streamingjobs/{jobName}/inputs/{inputName}/test, Length: 11"
    },
    {
      "metricName": "WeightedServiceInterfaceCount",
      "metricValue": 6.0,
      "additionalInformation": "Number of different operations: 6"
    },
    {
      "metricName": "AveragePathLength",
      "metricValue": 10.0
    },
    {
      "metricName": "DataWeight",
      "metricValue": 56.0
    },
    {
      "metricName": "NumberOfRootPaths",
      "metricValue": 1.0,
      "additionalInformation": "all root paths: /subscriptions"
    },
    {
      "metricName": "ServiceInterfaceDataCohesion",
      "metricValue": 0.6,
      "additionalInformation": "Metric value range: [0-1]; Set of pairwise operations with at least one common parameter: [[Inputs_Test, Inputs_ListByStreamingJob], [Inputs_Update, Inputs_CreateOrReplace], [Inputs_Get, Inputs_Test], [Inputs_Delete, Inputs_ListByStreamingJob], [Inputs_Delete, Inputs_CreateOrReplace], [Inputs_CreateOrReplace, Inputs_Get], [Inputs_Update, Inputs_Delete], [Inputs_Get, Inputs_ListByStreamingJob], [Inputs_CreateOrReplace, Inputs_ListByStreamingJob], [Inputs_Delete, Inputs_Test], [Inputs_CreateOrReplace, Inputs_Test], [Inputs_Delete, Inputs_Get], [Inputs_Update, Inputs_ListByStreamingJob], [Inputs_Update, Inputs_Get], [Inputs_Update, Inputs_Test]]; Set of pairwise operations with common return type: [[Inputs_Update, Inputs_CreateOrReplace], [Inputs_Update, Inputs_Get], [Inputs_CreateOrReplace, Inputs_Get]]; Number of operations: 6.0"
    }
  ]
}