{
  "apiTitle": "Firebase Rules",
  "apiVersion": "v1",
  "apiFileName": "googleapis.com-firebaserules-v1-swagger.yaml",
  "apiFormat": "OPENAPI",
  "measurementDate": "2019/12/13",
  "measurement": [
    {
      "metricName": "AveragePathLength",
      "metricValue": 2.4
    },
    {
      "metricName": "DataWeight",
      "metricValue": 152.0
    },
    {
      "metricName": "WeightedServiceInterfaceCount",
      "metricValue": 9.0,
      "additionalInformation": "Number of different operations: 9"
    },
    {
      "metricName": "LackOfMessageLevelCohesion",
      "metricValue": 0.5541
    },
    {
      "metricName": "ServiceInterfaceDataCohesion",
      "metricValue": 0.5417,
      "additionalInformation": "Metric value range: [0-1]; Set of pairwise operations with at least one common parameter: [[firebaserules.projects.test, firebaserules.projects.releases.create], [firebaserules.projects.test, firebaserules.projects.rulesets.create], [firebaserules.projects.test, firebaserules.projects.releases.get], [firebaserules.projects.releases.list, firebaserules.projects.releases.create], [firebaserules.projects.releases.list, firebaserules.projects.rulesets.create], [firebaserules.projects.releases.create, firebaserules.projects.releases.patch], [firebaserules.projects.releases.list, firebaserules.projects.releases.getExecutable], [firebaserules.projects.test, firebaserules.projects.releases.patch], [firebaserules.projects.releases.get, firebaserules.projects.rulesets.create], [firebaserules.projects.rulesets.list, firebaserules.projects.releases.getExecutable], [firebaserules.projects.releases.create, firebaserules.projects.releases.getExecutable], [firebaserules.projects.releases.list, firebaserules.projects.releases.patch], [firebaserules.projects.rulesets.create, firebaserules.projects.releases.patch], [firebaserules.projects.releases.get, firebaserules.projects.releases.patch], [firebaserules.projects.releases.getExecutable, firebaserules.projects.releases.patch], [firebaserules.projects.rulesets.list, firebaserules.projects.rulesets.create], [firebaserules.projects.releases.delete, firebaserules.projects.rulesets.create], [firebaserules.projects.releases.create, firebaserules.projects.rulesets.create], [firebaserules.projects.test, firebaserules.projects.rulesets.list], [firebaserules.projects.releases.list, firebaserules.projects.releases.get], [firebaserules.projects.test, firebaserules.projects.releases.getExecutable], [firebaserules.projects.releases.get, firebaserules.projects.rulesets.list], [firebaserules.projects.rulesets.list, firebaserules.projects.releases.delete], [firebaserules.projects.releases.delete, firebaserules.projects.releases.getExecutable], [firebaserules.projects.test, firebaserules.projects.releases.list], [firebaserules.projects.rulesets.create, firebaserules.projects.releases.getExecutable], [firebaserules.projects.releases.create, firebaserules.projects.releases.delete], [firebaserules.projects.rulesets.list, firebaserules.projects.releases.patch], [firebaserules.projects.releases.delete, firebaserules.projects.releases.patch], [firebaserules.projects.releases.create, firebaserules.projects.releases.get], [firebaserules.projects.releases.get, firebaserules.projects.releases.getExecutable], [firebaserules.projects.releases.create, firebaserules.projects.rulesets.list], [firebaserules.projects.releases.get, firebaserules.projects.releases.delete], [firebaserules.projects.test, firebaserules.projects.releases.delete], [firebaserules.projects.releases.list, firebaserules.projects.releases.delete], [firebaserules.projects.releases.list, firebaserules.projects.rulesets.list]]; Set of pairwise operations with common return type: [[firebaserules.projects.releases.create, firebaserules.projects.releases.get], [firebaserules.projects.releases.get, firebaserules.projects.releases.patch], [firebaserules.projects.releases.create, firebaserules.projects.releases.patch]]; Number of operations: 9.0"
    },
    {
      "metricName": "LongestPath",
      "metricValue": 3.0,
      "additionalInformation": "Longest path: /v1/{name}/releases, Length: 3"
    },
    {
      "metricName": "ArgumentsPerOperation",
      "metricValue": 13.2222
    },
    {
      "metricName": "BiggestRootCoverage",
      "metricValue": 1.0,
      "additionalInformation": "Biggest root coverage: /v1 with 9 operation(s) from overall 9 operation(s)"
    },
    {
      "metricName": "NumberOfRootPaths",
      "metricValue": 1.0,
      "additionalInformation": "all root paths: /v1"
    },
    {
      "metricName": "DistinctMessageRatio",
      "metricValue": 0.7778
    }
  ]
}